acme_challenge
