Metadata-Version: 1.1
Name: django-acme-challenge
Version: 1.2
Summary: A quick tool to serve the acme-challenge verification page.
Home-page: https://github.com/jamstooks/django-acme-challenge
Author: Benjamin W Stookey
Author-email: ben.stookey@gmail.com
License: UNKNOWN
Platform: UNKNOWN
Classifier: Environment :: Web Environment
Classifier: Intended Audience :: Developers
Classifier: License :: OSI Approved :: BSD License
Classifier: Operating System :: OS Independent
Classifier: Programming Language :: Python :: 2.7
Classifier: Programming Language :: Python :: 3.6
Classifier: Framework :: Django
